verification/simple_rtl/simple_mac_test.sv
// Simple MAC unit test - minimal RTL test
`timescale 1ns/1ps

module simple_mac_test;

    // Clock and reset
    logic clk;
    logic rst_n;
    
    // MAC unit inputs
    logic [15:0] a = 16'h0000;
    logic [15:0] b = 16'h0000;
    logic [31:0] c = 32'h00000000;
    logic valid = 0;
    
    // MAC unit outputs
    logic [31:0] result;
    logic ready;
    
    // Clock generation - 100MHz
    initial clk = 0;
    always #5 clk = ~clk;
    
    // Simple MAC unit (behavioral model for testing)
    always_ff @(posedge clk or negedge rst_n) begin
        if (!rst_n) begin
            result <= 32'h0;
            ready <= 1'b0;
        end else if (valid) begin
            result <= (a * b) + c;  // MAC operation: result = a * b + c
            ready <= 1'b1;
        end else begin
            ready <= 1'b0;
        end
    end
    
    // Test sequence
    initial begin
        rst_n = 0;
        $display("Starting simple MAC RTL test...");
        
        // Reset sequence
        rst_n = 0;
        repeat(10) @(posedge clk);
        rst_n = 1;
        $display("Reset released");
        
        // Test case 1: 2 * 3 + 4 = 10
        repeat(2) @(posedge clk);
        a = 16'd2;
        b = 16'd3;
        c = 32'd4;
        valid = 1;
        @(posedge clk);
        valid = 0;
        
        // Wait for result
        wait(ready);
        @(posedge clk);
        
        if (result == 32'd10) begin
            $display("✅ Test 1 PASSED: 2 * 3 + 4 = %0d", result);
        end else begin
            $display("❌ Test 1 FAILED: Expected 10, got %0d", result);
        end
        
        // Test case 2: 5 * 7 + 1 = 36
        repeat(2) @(posedge clk);
        a = 16'd5;
        b = 16'd7;
        c = 32'd1;
        valid = 1;
        @(posedge clk);
        valid = 0;
        
        // Wait for result
        wait(ready);
        @(posedge clk);
        
        if (result == 32'd36) begin
            $display("✅ Test 2 PASSED: 5 * 7 + 1 = %0d", result);
        end else begin
            $display("❌ Test 2 FAILED: Expected 36, got %0d", result);
        end
        
        // Test case 3: 0 * 100 + 50 = 50
        repeat(2) @(posedge clk);
        a = 16'd0;
        b = 16'd100;
        c = 32'd50;
        valid = 1;
        @(posedge clk);
        valid = 0;
        
        // Wait for result
        wait(ready);
        @(posedge clk);
        
        if (result == 32'd50) begin
            $display("✅ Test 3 PASSED: 0 * 100 + 50 = %0d", result);
        end else begin
            $display("❌ Test 3 FAILED: Expected 50, got %0d", result);
        end
        
        repeat(10) @(posedge clk);
        $display("Simple MAC RTL test completed successfully!");
        $finish;
    end
    
    // Timeout watchdog
    initial begin
        #10000; // 10us timeout
        $display("ERROR: Test timeout!");
        $finish;
    end
    
    // Generate VCD for waveform viewing
    initial begin
        $dumpfile("simple_mac_test.vcd");
        $dumpvars(0, simple_mac_test);
    end

endmodule

verification/simple_rtl/simple_mac_test.vcd
$date
	Sun Aug 31 00:17:42 2025
$end
$version
	Icarus Verilog
$end
$timescale
	1ps
$end
$scope module simple_mac_test $end
$var reg 16 ! a [15:0] $end
$var reg 16 " b [15:0] $end
$var reg 32 # c [31:0] $end
$var reg 1 $ clk $end
$var reg 1 % ready $end
$var reg 32 & result [31:0] $end
$var reg 1 ' rst_n $end
$var reg 1 ( valid $end
$upscope $end
$enddefinitions $end
$comment Show the parameter values. $end
$dumpall
$end
#0
$dumpvars
0(
0'
b0 &
0%
0$
b0 #
b0 "
b0 !
$end
#5000
1$
#10000
0$
#15000
1$
#20000
0$
#25000
1$
#30000
0$
#35000
1$
#40000
0$
#45000
1$
#50000
0$
#55000
1$
#60000
0$
#65000
1$
#70000
0$
#75000
1$
#80000
0$
#85000
1$
#90000
0$
#95000
1'
1$
#100000
0$
#105000
1$
#110000
0$
#115000
1(
b100 #
b11 "
b10 !
1$
#120000
0$
#125000
1%
b1010 &
0(
1$
#130000
0$
#135000
0%
1$
#140000
0$
#145000
1$
#150000
0$
#155000
1(
b1 #
b111 "
b101 !
1$
#160000
0$
#165000
1%
b100100 &
0(
1$
#170000
0$
#175000
0%
1$
#180000
0$
#185000
1$
#190000
0$
#195000
1(
b110010 #
b1100100 "
b0 !
1$
#200000
0$
#205000
1%
b110010 &
0(
1$
#210000
0$
#215000
0%
1$
