verification/simple_rtl/simple_tpu_mac.sv
// Simplified TPU MAC unit for Icarus Verilog compatibility
`timescale 1ns/1ps

module simple_tpu_mac #(
    parameter DATA_WIDTH = 32
) (
    input  logic                    clk,
    input  logic                    rst_n,
    input  logic                    enable,
    input  logic [2:0]              data_type,
    input  logic [15:0]             a_data,
    input  logic [15:0]             b_data,
    input  logic [31:0]             c_data,
    input  logic                    valid_in,
    
    output logic [31:0]             result,
    output logic                    valid_out,
    output logic                    ready
);

    // Internal registers
    logic [31:0] mac_result;
    logic        result_valid;
    
    // MAC operation: result = a * b + c
    always_ff @(posedge clk or negedge rst_n) begin
        if (!rst_n) begin
            mac_result <= 32'h0;
            result_valid <= 1'b0;
        end else if (enable && valid_in) begin
            // Perform MAC operation based on data type
            case (data_type)
                3'b000: begin // INT8
                    mac_result <= (a_data[7:0] * b_data[7:0]) + c_data;
                end
                3'b001: begin // INT16
                    mac_result <= (a_data * b_data) + c_data;
                end
                3'b010: begin // INT32
                    mac_result <= (a_data * b_data) + c_data;
                end
                default: begin
                    mac_result <= (a_data * b_data) + c_data;
                end
            endcase
            result_valid <= 1'b1;
        end else begin
            result_valid <= 1'b0;
        end
    end
    
    // Output assignments
    assign result = mac_result;
    assign valid_out = result_valid;
    assign ready = enable;

endmodule

verification/simple_rtl/test_simple_tpu_mac.sv
// Test simplified TPU MAC unit
`timescale 1ns/1ps

module test_simple_tpu_mac;

    // Clock and reset
    logic clk;
    logic rst_n;
    
    // TPU MAC unit interface
    logic enable;
    logic [2:0] data_type;
    logic [15:0] a_data;
    logic [15:0] b_data;
    logic [31:0] c_data;
    logic valid_in;
    
    logic [31:0] result;
    logic valid_out;
    logic ready;
    
    // Clock generation - 100MHz
    initial clk = 0;
    always #5 clk = ~clk;
    
    // Instantiate the simplified TPU MAC unit
    simple_tpu_mac #(
        .DATA_WIDTH(32)
    ) dut (
        .clk(clk),
        .rst_n(rst_n),
        .enable(enable),
        .data_type(data_type),
        .a_data(a_data),
        .b_data(b_data),
        .c_data(c_data),
        .valid_in(valid_in),
        .result(result),
        .valid_out(valid_out),
        .ready(ready)
    );
    
    // Test sequence
    initial begin
        $display("🔬 Testing Simplified TPU MAC Unit RTL Code");
        $display("==========================================");
        
        // Initialize signals
        rst_n = 0;
        enable = 0;
        data_type = 3'b000; // INT8
        a_data = 16'h0000;
        b_data = 16'h0000;
        c_data = 32'h00000000;
        valid_in = 0;
        
        // Reset sequence
        repeat(10) @(posedge clk);
        rst_n = 1;
        enable = 1;
        $display("✅ Reset released, TPU MAC unit enabled");
        
        // Test case 1: Basic MAC operation (INT8)
        repeat(2) @(posedge clk);
        data_type = 3'b000; // INT8
        a_data = 16'd10;
        b_data = 16'd20;
        c_data = 32'd5;
        valid_in = 1;
        @(posedge clk);
        valid_in = 0;
        
        // Wait for result
        wait(valid_out);
        @(posedge clk);
        
        $display("🧮 Test 1 (INT8): 10 * 20 + 5 = %0d", result);
        if (result == 32'd205) begin
            $display("✅ Test 1 PASSED");
        end else begin
            $display("❌ Test 1 FAILED: Expected 205, got %0d", result);
        end
        
        // Test case 2: INT16 operation
        repeat(5) @(posedge clk);
        data_type = 3'b001; // INT16
        a_data = 16'd7;
        b_data = 16'd8;
        c_data = 32'd100;
        valid_in = 1;
        @(posedge clk);
        valid_in = 0;
        
        // Wait for result
        wait(valid_out);
        @(posedge clk);
        
        $display("🧮 Test 2 (INT16): 7 * 8 + 100 = %0d", result);
        if (result == 32'd156) begin
            $display("✅ Test 2 PASSED");
        end else begin
            $display("❌ Test 2 FAILED: Expected 156, got %0d", result);
        end
        
        // Test case 3: INT32 operation
        repeat(5) @(posedge clk);
        data_type = 3'b010; // INT32
        a_data = 16'd15;
        b_data = 16'd4;
        c_data = 32'd25;
        valid_in = 1;
        @(posedge clk);
        valid_in = 0;
        
        // Wait for result
        wait(valid_out);
        @(posedge clk);
        
        $display("🧮 Test 3 (INT32): 15 * 4 + 25 = %0d", result);
        if (result == 32'd85) begin
            $display("✅ Test 3 PASSED");
        end else begin
            $display("❌ Test 3 FAILED: Expected 85, got %0d", result);
        end
        
        // Test case 4: Zero multiplication
        repeat(5) @(posedge clk);
        a_data = 16'd0;
        b_data = 16'd999;
        c_data = 32'd42;
        valid_in = 1;
        @(posedge clk);
        valid_in = 0;
        
        // Wait for result
        wait(valid_out);
        @(posedge clk);
        
        $display("🧮 Test 4 (Zero): 0 * 999 + 42 = %0d", result);
        if (result == 32'd42) begin
            $display("✅ Test 4 PASSED");
        end else begin
            $display("❌ Test 4 FAILED: Expected 42, got %0d", result);
        end
        
        repeat(10) @(posedge clk);
        $display("");
        $display("🎉 TPU MAC RTL 测试完成!");
        $display("✨ 成功执行了 RTL 硬件描述代码!");
        $display("🔧 这是真正的硬件逻辑仿真，不是软件模拟!");
        $finish;
    end
    
    // Timeout watchdog
    initial begin
        #100000; // 100us timeout
        $display("❌ ERROR: Test timeout!");
        $finish;
    end
    
    // Generate VCD for waveform viewing
    initial begin
        $dumpfile("test_simple_tpu_mac.vcd");
        $dumpvars(0, test_simple_tpu_mac);
    end

endmodule

verification/simple_rtl/test_simple_tpu_mac.vcd
$date
	Sun Aug 31 00:17:25 2025
$end
$version
	Icarus Verilog
$end
$timescale
	1ps
$end
$scope module test_simple_tpu_mac $end
$var wire 1 ! valid_out $end
$var wire 32 " result [31:0] $end
$var wire 1 # ready $end
$var reg 16 $ a_data [15:0] $end
$var reg 16 % b_data [15:0] $end
$var reg 32 & c_data [31:0] $end
$var reg 1 ' clk $end
$var reg 3 ( data_type [2:0] $end
$var reg 1 ) enable $end
$var reg 1 * rst_n $end
$var reg 1 + valid_in $end
$scope module dut $end
$var wire 16 , a_data [15:0] $end
$var wire 16 - b_data [15:0] $end
$var wire 32 . c_data [31:0] $end
$var wire 1 ' clk $end
$var wire 3 / data_type [2:0] $end
$var wire 1 ) enable $end
$var wire 1 # ready $end
$var wire 32 0 result [31:0] $end
$var wire 1 * rst_n $end
$var wire 1 + valid_in $end
$var wire 1 ! valid_out $end
$var parameter 32 1 DATA_WIDTH $end
$var reg 32 2 mac_result [31:0] $end
$var reg 1 3 result_valid $end
$upscope $end
$upscope $end
$enddefinitions $end
$comment Show the parameter values. $end
$dumpall
b100000 1
$end
#0
$dumpvars
03
b0 2
b0 0
b0 /
b0 .
b0 -
b0 ,
0+
0*
0)
b0 (
0'
b0 &
b0 %
b0 $
0#
b0 "
0!
$end
#5000
1'
#10000
0'
#15000
1'
#20000
0'
#25000
1'
#30000
0'
#35000
1'
#40000
0'
#45000
1'
#50000
0'
#55000
1'
#60000
0'
#65000
1'
#70000
0'
#75000
1'
#80000
0'
#85000
1'
#90000
0'
#95000
1#
1)
1*
1'
#100000
0'
#105000
1'
#110000
0'
#115000
1!
13
b11001101 "
b11001101 0
b11001101 2
1+
b101 &
b101 .
b10100 %
b10100 -
b1010 $
b1010 ,
1'
#120000
0'
#125000
0!
03
0+
1'
#130000
0'
#135000
1'
#140000
0'
#145000
1'
#150000
0'
#155000
1'
#160000
0'
#165000
1'
#170000
0'
#175000
1'
#180000
0'
#185000
1!
13
b10011100 "
b10011100 0
b10011100 2
1+
b1100100 &
b1100100 .
b1000 %
b1000 -
b111 $
b111 ,
b1 (
b1 /
1'
#190000
0'
#195000
0!
03
0+
1'
#200000
0'
#205000
1'
#210000
0'
#215000
1'
#220000
0'
#225000
1'
#230000
0'
#235000
1'
#240000
0'
#245000
1'
#250000
0'
#255000
1!
13
b1010101 "
b1010101 0
b1010101 2
1+
b11001 &
b11001 .
b100 %
b100 -
b1111 $
b1111 ,
b10 (
b10 /
1'
#260000
0'
#265000
0!
03
0+
1'
#270000
0'
#275000
1'
#280000
0'
#285000
1'
#290000
0'
#295000
1'
#300000
0'
#305000
1'
#310000
0'
#315000
1'
#320000
0'
#325000
1!
13
b101010 "
b101010 0
b101010 2
1+
b101010 &
b101010 .
b1111100111 %
b1111100111 -
b0 $
b0 ,
1'
#330000
0'
#335000
0!
03
0+
1'
